glob2regex/__init__.py
glob2regex/py.typed
glob2regex-0.1.0.dist-info/licenses/LICENSE
glob2regex-0.1.0.dist-info/METADATA
glob2regex-0.1.0.dist-info/WHEEL
glob2regex-0.1.0.dist-info/top_level.txt
glob2regex-0.1.0.dist-info/RECORD
